beangrep/__init__.py
beangrep/__main__.py
beangrep/beangrep.py
beangrep/cli.py
beangrep/data/.gitkeep
beangrep/data/bean-grep.1
beangrep-0.6.0.dist-info/LICENSE-GPL-2.0-or-later
beangrep-0.6.0.dist-info/METADATA
beangrep-0.6.0.dist-info/WHEEL
beangrep-0.6.0.dist-info/entry_points.txt
beangrep-0.6.0.dist-info/top_level.txt
beangrep-0.6.0.dist-info/RECORD
