Metadata-Version: 2.1
Name: beangrep
Version: 0.6.0
Summary: Grep-like filter for the Beancount plain text accounting system
Author-email: Stefano Zacchiroli <zack@upsilon.cc>
License: GPL-2.0-or-later
Project-URL: Homepage, https://github.com/zacchiro/beangrep
Project-URL: Issues, https://github.com/zacchiro/beangrep/issues
Keywords: accounting,beancount,grep,ledger,plaintext,plaintext-accounting
Classifier: Programming Language :: Python :: 3
Classifier: License :: OSI Approved :: GNU General Public License v2 (GPLv2)
Classifier: Topic :: Office/Business :: Financial :: Accounting
Classifier: Topic :: Text Processing :: General
Requires-Python: >=3.11
License-File: LICENSE-GPL-2.0-or-later
Requires-Dist: beancount >=2.3.5
Requires-Dist: click >=8.1
Provides-Extra: dev
Requires-Dist: black ==23.1 ; extra == 'dev'
Requires-Dist: flake8 >=5 ; extra == 'dev'
Requires-Dist: mypy >=1 ; extra == 'dev'
Requires-Dist: pre-commit ; extra == 'dev'
Requires-Dist: pytest >=7.2 ; extra == 'dev'
Requires-Dist: pytest-cov >=4 ; extra == 'dev'
